ml_sniff/__init__.py
ml_sniff/cli.py
ml_sniff/gui.py
ml_sniff/sniffer.py
ml_sniff-1.0.0.dist-info/licenses/LICENSE
ml_sniff-1.0.0.dist-info/METADATA
ml_sniff-1.0.0.dist-info/WHEEL
ml_sniff-1.0.0.dist-info/entry_points.txt
ml_sniff-1.0.0.dist-info/top_level.txt
ml_sniff-1.0.0.dist-info/RECORD
