Metadata-Version: 2.4
Name: ml-sniff
Version: 1.0.0
Summary: Advanced Machine Learning Problem Detection with CLI and GUI interfaces
Home-page: https://github.com/Sherin-SEF-AI/ml-sniffer
Author: Sherin Joseph Roy
Author-email: Sherin Joseph Roy <sherin.joseph2217@gmail.com>
Maintainer-email: Sherin Joseph Roy <sherin.joseph2217@gmail.com>
License: MIT
Project-URL: Homepage, https://github.com/Sherin-SEF-AI/ml-sniffer
Project-URL: Documentation, https://github.com/Sherin-SEF-AI/ml-sniffer#readme
Project-URL: Repository, https://github.com/Sherin-SEF-AI/ml-sniffer
Project-URL: Bug Tracker, https://github.com/Sherin-SEF-AI/ml-sniffer/issues
Project-URL: Author Website, https://sherin-sef-ai.github.io/
Keywords: machine-learning,data-analysis,classification,regression,clustering,automation,streamlit,gui
Classifier: Development Status :: 5 - Production/Stable
Classifier: Intended Audience :: Developers
Classifier: Intended Audience :: Science/Research
Classifier: License :: OSI Approved :: MIT License
Classifier: Operating System :: OS Independent
Classifier: Programming Language :: Python :: 3
Classifier: Programming Language :: Python :: 3.8
Classifier: Programming Language :: Python :: 3.9
Classifier: Programming Language :: Python :: 3.10
Classifier: Programming Language :: Python :: 3.11
Classifier: Programming Language :: Python :: 3.12
Classifier: Topic :: Scientific/Engineering :: Artificial Intelligence
Classifier: Topic :: Software Development :: Libraries :: Python Modules
Classifier: Topic :: Scientific/Engineering :: Information Analysis
Requires-Python: >=3.7
License-File: LICENSE
Requires-Dist: pandas>=1.3.0
Requires-Dist: numpy>=1.20.0
Requires-Dist: matplotlib>=3.3.0
Requires-Dist: seaborn>=0.11.0
Requires-Dist: scikit-learn>=1.0.0
Requires-Dist: scipy>=1.7.0
Requires-Dist: plotly>=5.0.0
Requires-Dist: streamlit>=1.28.0
Requires-Dist: streamlit-option-menu>=0.3.0
Requires-Dist: streamlit-aggrid>=0.3.0
Provides-Extra: dev
Requires-Dist: pytest>=6.0; extra == "dev"
Requires-Dist: pytest-cov>=2.0; extra == "dev"
Requires-Dist: black>=21.0; extra == "dev"
Requires-Dist: flake8>=3.8; extra == "dev"
Requires-Dist: mypy>=0.800; extra == "dev"
Dynamic: author
Dynamic: home-page
Dynamic: license-file
Dynamic: requires-python
